MANIFEST.in
README.md
change.log
setup.py
ppss_pyramidutils/__init__.py
ppss_pyramidutils/appsettings.py
ppss_pyramidutils/backgroundjobs.py
ppss_pyramidutils/cryptoutils.py
ppss_pyramidutils/filemanager.py
ppss_pyramidutils/jsonutils.py
ppss_pyramidutils/modelbase.py
ppss_pyramidutils/scriptbase.py
ppss_pyramidutils/sessionhandling.py
ppss_pyramidutils/utf8csv.py
ppss_pyramidutils/utils.py
ppss_pyramidutils.egg-info/PKG-INFO
ppss_pyramidutils.egg-info/SOURCES.txt
ppss_pyramidutils.egg-info/dependency_links.txt
ppss_pyramidutils.egg-info/entry_points.txt
ppss_pyramidutils.egg-info/requires.txt
ppss_pyramidutils.egg-info/top_level.txt
ppss_pyramidutils/scripts/__init__.py
ppss_pyramidutils/scripts/make_ini.py