Metadata-Version: 2.1
Name: ppss_pyramidutils
Version: 1.6.4.1
Summary: Simple utils to handle data from ini files in Pyramid for python 2.7 & 3
Author: pdepmcp
Author-email: pdepmcp@gmail.com
Keywords: pyramid module utils accelerator
Classifier: Development Status :: 5 - Production/Stable
Classifier: Operating System :: OS Independent
Classifier: Framework :: Pyramid
Classifier: Intended Audience :: Developers
Classifier: Programming Language :: Python :: 2
Classifier: Programming Language :: Python :: 2.7
Classifier: Programming Language :: Python :: 3.6
Requires-Dist: six
Requires-Dist: sqlalchemy_utils
Requires-Dist: cryptography
Requires-Dist: pycryptodome
Requires-Dist: sqlalchemy
Requires-Dist: jinja2
